dep_check/__init__.py
dep_check/checker.py
dep_check/dependency_finder.py
dep_check/main.py
dep_check/models.py
dep_check/infra/__init__.py
dep_check/infra/file_system.py
dep_check/infra/io.py
dep_check/infra/python_parser.py
dep_check/infra/std_lib_filter.py
dep_check/use_cases/__init__.py
dep_check/use_cases/app_configuration.py
dep_check/use_cases/build.py
dep_check/use_cases/check.py
dep_check/use_cases/draw_graph.py
dep_check/use_cases/interfaces.py
dep_check-3.1.0.dist-info/LICENSE
dep_check-3.1.0.dist-info/METADATA
dep_check-3.1.0.dist-info/WHEEL
dep_check-3.1.0.dist-info/entry_points.txt
dep_check-3.1.0.dist-info/top_level.txt
dep_check-3.1.0.dist-info/RECORD
