Metadata-Version: 2.1
Name: dep-check
Version: 3.1.0
Summary: Python Dependency Check Tool
Home-page: https://github.com/lumapps/dep-check
Download-URL: https://github.com/lumapps/dep-check/tarball/master
Author: LumApps
Author-email: core-devs@lumapps.com
License: MIT License
Keywords: python,Dependency,linter,architecture,quality,dep-check,dep_check
Classifier: Development Status :: 2 - Pre-Alpha
Classifier: Intended Audience :: Developers
Classifier: License :: OSI Approved :: MIT License
Classifier: Natural Language :: English
Classifier: Programming Language :: Python :: 3.9
Classifier: Programming Language :: Python :: 3.10
Classifier: Programming Language :: Python :: 3.11
License-File: LICENSE
Requires-Dist: Click
Requires-Dist: PyYAML
Requires-Dist: Jinja2
Requires-Dist: ordered-set
